mondialrelay/utils.py
mondialrelay/api.py
mondialrelay/picking.py
mondialrelay/__init__.py
mondialrelay/template/v1_picking_send.xml
mondialrelay-0.0.1.dist-info/METADATA
mondialrelay-0.0.1.dist-info/RECORD
mondialrelay-0.0.1.dist-info/WHEEL
mondialrelay-0.0.1.dist-info/top_level.txt
mondialrelay-0.0.1.dist-info/DESCRIPTION.rst
mondialrelay-0.0.1.dist-info/metadata.json
