Metadata-Version: 2.0
Name: mondialrelay
Version: 0.0.1
Summary: Python API MondialRelay carrier
Home-page: https://www.nan-tic.com
Author: NaN-TIC
Author-email: info@nan-tic.com
License: GPL-3
Download-URL: https://bitbucket.org/nantic/python-mondialrelay
Platform: UNKNOWN
Classifier: Development Status :: 4 - Beta
Classifier: Environment :: Web Environment
Classifier: Intended Audience :: Developers
Classifier: License :: OSI Approved :: GNU Affero General Public License v3
Classifier: Operating System :: OS Independent
Classifier: Programming Language :: Python
Classifier: Topic :: Internet :: WWW/HTTP :: Dynamic Content
Classifier: Topic :: Software Development :: Libraries :: Python Modules
Requires-Dist: genshi
